pytest_match_skip/__init__.py
pytest_match_skip/check_skip_prefixes.py
pytest_match_skip/hooks.py
pytest_match_skip/plugin.py
pytest_match_skip-0.2.1.dist-info/DESCRIPTION.rst
pytest_match_skip-0.2.1.dist-info/METADATA
pytest_match_skip-0.2.1.dist-info/RECORD
pytest_match_skip-0.2.1.dist-info/WHEEL
pytest_match_skip-0.2.1.dist-info/entry_points.txt
pytest_match_skip-0.2.1.dist-info/metadata.json
pytest_match_skip-0.2.1.dist-info/top_level.txt
