Metadata-Version: 2.0
Name: pytest-match-skip
Version: 0.2.1
Summary: Skip matching marks. Matches partial marks using wildcards.
Home-page: https://github.com/jsfehler/pytest-match-skip
Author: Joshua Fehler
Author-email: jsfehler@gmail.com
Maintainer: Joshua Fehler
Maintainer-email: jsfehler@gmail.com
License: MIT
Platform: UNKNOWN
Classifier: Development Status :: 4 - Beta
Classifier: Framework :: Pytest
Classifier: Intended Audience :: Developers
Classifier: Topic :: Software Development :: Testing
Classifier: Programming Language :: Python
Classifier: Programming Language :: Python :: 2
Classifier: Programming Language :: Python :: 2.7
Classifier: Programming Language :: Python :: 3
Classifier: Programming Language :: Python :: 3.4
Classifier: Programming Language :: Python :: 3.5
Classifier: Programming Language :: Python :: 3.6
Classifier: Programming Language :: Python :: Implementation :: CPython
Classifier: Programming Language :: Python :: Implementation :: PyPy
Classifier: Operating System :: OS Independent
Classifier: License :: OSI Approved :: MIT License
Requires-Dist: pytest (>=4.4.1)
